spoken_macedonian_annotation/__init__.py
spoken_macedonian_annotation/all_data.json
spoken_macedonian_annotation/annotate.py
spoken_macedonian_annotation/cli.py
spoken_macedonian_annotation/file_processing.py
spoken_macedonian_annotation/homonyms.py
spoken_macedonian_annotation-1.0.0.dist-info/LICENSE
spoken_macedonian_annotation-1.0.0.dist-info/METADATA
spoken_macedonian_annotation-1.0.0.dist-info/WHEEL
spoken_macedonian_annotation-1.0.0.dist-info/entry_points.txt
spoken_macedonian_annotation-1.0.0.dist-info/top_level.txt
spoken_macedonian_annotation-1.0.0.dist-info/RECORD
