Metadata-Version: 2.1
Name: spoken-macedonian-annotation
Version: 1.0.0
Summary: Library and CLI to for simple morphological annotation of spoken Macedonian
Home-page: UNKNOWN
Author: Anastasia Escher
License: UNKNOWN
Platform: UNKNOWN
Classifier: Programming Language :: Python :: 3
Classifier: License :: OSI Approved :: MIT License
Classifier: Operating System :: OS Independent
Requires-Python: >=3.8
License-File: LICENSE
Requires-Dist: nltk (>=3.4.5)
